LICENSE.rst
MANIFEST.in
README.rst
TODO.rst
setup.py
Flask_Fundatio.egg-info/PKG-INFO
Flask_Fundatio.egg-info/SOURCES.txt
Flask_Fundatio.egg-info/dependency_links.txt
Flask_Fundatio.egg-info/requires.txt
Flask_Fundatio.egg-info/top_level.txt
flask_fundatio/__init__.py
flask_fundatio/static/css/accessibility_foundicons.css
flask_fundatio/static/css/foundation.css
flask_fundatio/static/css/foundation.min.css
flask_fundatio/static/css/foundicons.css
flask_fundatio/static/css/general_enclosed_foundicons.css
flask_fundatio/static/css/general_foundicons.css
flask_fundatio/static/css/normalize.css
flask_fundatio/static/css/social_foundicons.css
flask_fundatio/static/fonts/accessibility_foundicons.eot
flask_fundatio/static/fonts/accessibility_foundicons.svg
flask_fundatio/static/fonts/accessibility_foundicons.ttf
flask_fundatio/static/fonts/accessibility_foundicons.woff
flask_fundatio/static/fonts/general_enclosed_foundicons.eot
flask_fundatio/static/fonts/general_enclosed_foundicons.svg
flask_fundatio/static/fonts/general_enclosed_foundicons.ttf
flask_fundatio/static/fonts/general_enclosed_foundicons.woff
flask_fundatio/static/fonts/general_foundicons.eot
flask_fundatio/static/fonts/general_foundicons.svg
flask_fundatio/static/fonts/general_foundicons.ttf
flask_fundatio/static/fonts/general_foundicons.woff
flask_fundatio/static/fonts/social_foundicons.eot
flask_fundatio/static/fonts/social_foundicons.svg
flask_fundatio/static/fonts/social_foundicons.ttf
flask_fundatio/static/fonts/social_foundicons.woff
flask_fundatio/static/js/foundation.min.js
flask_fundatio/static/js/foundation/foundation.alerts.js
flask_fundatio/static/js/foundation/foundation.clearing.js
flask_fundatio/static/js/foundation/foundation.cookie.js
flask_fundatio/static/js/foundation/foundation.dropdown.js
flask_fundatio/static/js/foundation/foundation.forms.js
flask_fundatio/static/js/foundation/foundation.interchange.js
flask_fundatio/static/js/foundation/foundation.joyride.js
flask_fundatio/static/js/foundation/foundation.js
flask_fundatio/static/js/foundation/foundation.magellan.js
flask_fundatio/static/js/foundation/foundation.orbit.js
