Metadata-Version: 1.0
Name: Flask-Fundatio
Version: 0.1
Summary: Flask extension to integrate the Foundation front-end framework
Home-page: https://github.com/wbolster/flask-fundatio
Author: Wouter Bolsterlee
Author-email: uws@xs4all.nl
License: BSD
Platform: UNKNOWN
